{"list": [{"id": "080201", "label": "080201 - Analysis of Algorithms and Complexity"}, {"id": "080202", "label": "080202 - Applied Discrete Mathematics"}, {"id": "080203", "label": "080203 - Computational Logic and Formal Languages"}, {"id": "080204", "label": "080204 - Mathematical Software"}, {"id": "080205", "label": "080205 - Numerical Computation"}, {"id": "080299", "label": "080299 - Computation Theory and Mathematics not elsewhere classified"}], "selectable": 1, "namespace": "http://purl.org/anzsrc/for#"}